torchzap/__init__.py
torchzap/preprocessing.py
torchzap/trainer.py
torchzap-23.4.18.19.dist-info/METADATA
torchzap-23.4.18.19.dist-info/WHEEL
torchzap-23.4.18.19.dist-info/top_level.txt
torchzap-23.4.18.19.dist-info/RECORD
