Metadata-Version: 2.1
Name: torchzap
Version: 23.4.18.19
Summary: PyTorch Zap
Home-page: https://github.com/private_repo/
Author: tompz
Author-email: mailto@gmail.com
Classifier: Programming Language :: Python :: 3
Classifier: License :: OSI Approved :: MIT License
Classifier: Operating System :: OS Independent
Requires-Dist: fire
Requires-Dist: codefast (>=0.9.9)
Requires-Dist: pydantic
Requires-Dist: pandas
Requires-Dist: torch
Requires-Dist: tqdm
Requires-Dist: transformers
